{
    "CapturedObjects": [
        {
            "ActorName": "TRAFFIC_SIGN 610",
            "ObjectId": 610,
            "BoundingBox3D Origin X": 6.857398665880282,
            "BoundingBox3D Origin Y": 10.66117956751259,
            "BoundingBox3D Origin Z": 2.41535446420312,
            "BoundingBox3D Extent X": 0.1,
            "BoundingBox3D Extent Y": 0.5673764564289475,
            "BoundingBox3D Extent Z": 0.8397778011530023,
            "BoundingBox3D Orientation Quat W": -0.1642450091437362,
            "BoundingBox3D Orientation Quat X": 0.0018221982111354,
            "BoundingBox3D Orientation Quat Y": 0.0120504321660076,
            "BoundingBox3D Orientation Quat Z": 0.9863442825148152,
            "ObjectType": "TRAFFIC_SIGN",
            "Occluded": {
                "F_CTCAM_L": 0.0
            },
            "Truncated": 0,
            "ObjectMeta": {
                "SourceID": 610,
                "SubType": "us_yellow_ground_diamond_unknown",
                "Text": "",
                "OcrVersion": 10006
            }
        },
        {
            "ActorName": "TRAFFIC_SIGN 611",
            "ObjectId": 611,
            "BoundingBox3D Origin X": 16.352956050013745,
            "BoundingBox3D Origin Y": -4.4934018008061685,
            "BoundingBox3D Origin Z": 2.427409466356039,
            "BoundingBox3D Extent X": 0.1,
            "BoundingBox3D Extent Y": 0.6647898721773063,
            "BoundingBox3D Extent Z": 0.4925958622564428,
            "BoundingBox3D Orientation Quat W": 0.0831659725866501,
            "BoundingBox3D Orientation Quat X": -0.0011933317671504,
            "BoundingBox3D Orientation Quat Y": 0.0121273187638155,
            "BoundingBox3D Orientation Quat Z": 0.996461201002132,
            "ObjectType": "TRAFFIC_SIGN",
            "Occluded": {
                "F_MIDRANGECAM_C": 4.902190994471312e-06
            },
            "Truncated": 0,
            "ObjectMeta": {
                "SourceID": 611,
                "SubType": "unknown",
                "Text": "P",
                "OcrVersion": 10006
            }
        },
        {
            "ActorName": "TRAFFIC_SIGN 612",
            "ObjectId": 612,
            "BoundingBox3D Origin X": 52.8874945354014,
            "BoundingBox3D Origin Y": -3.991149039065931,
            "BoundingBox3D Origin Z": 5.203690283000469,
            "BoundingBox3D Extent X": 0.1,
            "BoundingBox3D Extent Y": 2.015689627696113,
            "BoundingBox3D Extent Z": 0.6071013615992222,
            "BoundingBox3D Orientation Quat W": 0.0445256001712963,
            "BoundingBox3D Orientation Quat X": -0.0007210774276535,
            "BoundingBox3D Orientation Quat Y": 0.0121647171871902,
            "BoundingBox3D Orientation Quat Z": 0.9989339170498144,
            "ObjectType": "TRAFFIC_SIGN",
            "Occluded": {
                "F_MIDRANGECAM_C": 0.0022245720028877
            },
            "Truncated": 0,
            "ObjectMeta": {
                "SourceID": 612,
                "SubType": "unknown",
                "Text": "",
                "OcrVersion": 10006
            }
        },
        {
            "ActorName": "TRAFFIC_SIGN 613",
            "ObjectId": 613,
            "BoundingBox3D Origin X": 58.45128502678381,
            "BoundingBox3D Origin Y": -4.349646086222492,
            "BoundingBox3D Origin Z": 2.696704786270857,
            "BoundingBox3D Extent X": 0.1,
            "BoundingBox3D Extent Y": 0.821519601845871,
            "BoundingBox3D Extent Z": 1.04655705856691,
            "BoundingBox3D Orientation Quat W": 0.0454457633380842,
            "BoundingBox3D Orientation Quat X": -0.0007294655006296,
            "BoundingBox3D Orientation Quat Y": 0.0121639359826614,
            "BoundingBox3D Orientation Quat Z": 0.9988924812691864,
            "ObjectType": "TRAFFIC_SIGN",
            "Occluded": {
                "F_MIDRANGECAM_C": 1.4585447516424212e-08
            },
            "Truncated": 0,
            "ObjectMeta": {
                "SourceID": 613,
                "SubType": "unknown",
                "Text": "AHEAD",
                "OcrVersion": 10006
            }
        },
        {
            "ActorName": "TRAFFIC_SIGN 614",
            "ObjectId": 614,
            "BoundingBox3D Origin X": 39.62116876854452,
            "BoundingBox3D Origin Y": 15.423766192921905,
            "BoundingBox3D Origin Z": 1.9804294733330607,
            "BoundingBox3D Extent X": 0.1,
            "BoundingBox3D Extent Y": 0.7431382892211243,
            "BoundingBox3D Extent Z": 0.8068183363710659,
            "BoundingBox3D Orientation Quat W": -0.3943038499267772,
            "BoundingBox3D Orientation Quat X": 0.0046455398061294,
            "BoundingBox3D Orientation Quat Y": 0.0112719722985659,
            "BoundingBox3D Orientation Quat Z": 0.9188992521127288,
            "ObjectType": "TRAFFIC_SIGN",
            "Occluded": {
                "F_MIDRANGECAM_C": 0.9998637437820436
            },
            "Truncated": 0,
            "ObjectMeta": {
                "SourceID": 614,
                "SubType": "unknown",
                "Text": "",
                "OcrVersion": 10006
            }
        },
        {
            "ActorName": "TRAFFIC_SIGN 615",
            "ObjectId": 615,
            "BoundingBox3D Origin X": 47.532698954023545,
            "BoundingBox3D Origin Y": -11.328767386003165,
            "BoundingBox3D Origin Z": 2.7256358452141285,
            "BoundingBox3D Extent X": 0.1,
            "BoundingBox3D Extent Y": 0.7208321150109754,
            "BoundingBox3D Extent Z": 0.6150844709069305,
            "BoundingBox3D Orientation Quat W": 0.1691429063245141,
            "BoundingBox3D Orientation Quat X": -0.0022395751607538,
            "BoundingBox3D Orientation Quat Y": 0.0119786454069596,
            "BoundingBox3D Orientation Quat Z": 0.9855161965170388,
            "ObjectType": "TRAFFIC_SIGN",
            "Occluded": {
                "F_MIDRANGECAM_C": 0.8678969740867615
            },
            "Truncated": 0,
            "ObjectMeta": {
                "SourceID": 615,
                "SubType": "us_yellow_ground_diamond_unknown",
                "Text": "",
                "OcrVersion": 10006
            }
        },
        {
            "ActorName": "TRAFFIC_SIGN 616",
            "ObjectId": 616,
            "BoundingBox3D Origin X": 72.95054266231045,
            "BoundingBox3D Origin Y": -4.379785310738953,
            "BoundingBox3D Origin Z": 3.1722749331966043,
            "BoundingBox3D Extent X": 0.1,
            "BoundingBox3D Extent Y": 0.5572884027437033,
            "BoundingBox3D Extent Z": 0.5924573148805717,
            "BoundingBox3D Orientation Quat W": 0.0577669448607121,
            "BoundingBox3D Orientation Quat X": -0.0008805065326533,
            "BoundingBox3D Orientation Quat Y": 0.0121541362938704,
            "BoundingBox3D Orientation Quat Z": 0.9982557196233118,
            "ObjectType": "TRAFFIC_SIGN",
            "Occluded": {
                "F_MIDRANGECAM_C": 0.7764438986778259
            },
            "Truncated": 0,
            "ObjectMeta": {
                "SourceID": 616,
                "SubType": "unknown",
                "Text": "",
                "OcrVersion": 10006
            }
        },
        {
            "ActorName": "TRAFFIC_SIGN 617",
            "ObjectId": 617,
            "BoundingBox3D Origin X": 52.348566636978376,
            "BoundingBox3D Origin Y": -4.6557271117926575,
            "BoundingBox3D Origin Z": 3.0956506449729204,
            "BoundingBox3D Extent X": 0.0999999999999999,
            "BoundingBox3D Extent Y": 0.7647942581555,
            "BoundingBox3D Extent Z": 0.185378029919662,
            "BoundingBox3D Orientation Quat W": 0.1821227130811508,
            "BoundingBox3D Orientation Quat X": -0.002395214061871,
            "BoundingBox3D Orientation Quat Y": 0.0119483712464796,
            "BoundingBox3D Orientation Quat Z": 0.9832002933045304,
            "ObjectType": "TRAFFIC_SIGN",
            "Occluded": {
                "F_MIDRANGECAM_C": 0.9980132579803468
            },
            "Truncated": 0,
            "ObjectMeta": {
                "SourceID": 617,
                "SubType": "us_white_ground_rectangle_unknown",
                "Text": "",
                "OcrVersion": 10006
            }
        },
        {
            "ActorName": "TRAFFIC_SIGN 618",
            "ObjectId": 618,
            "BoundingBox3D Origin X": 74.71432342166463,
            "BoundingBox3D Origin Y": -3.8712948104948737,
            "BoundingBox3D Origin Z": 2.5732638221234083,
            "BoundingBox3D Extent X": 0.0999999999999999,
            "BoundingBox3D Extent Y": 0.3186681614729488,
            "BoundingBox3D Extent Z": 0.468749094353403,
            "BoundingBox3D Orientation Quat W": 0.2932561889218925,
            "BoundingBox3D Orientation Quat X": -0.0037428559505826,
            "BoundingBox3D Orientation Quat Y": 0.0115970901145845,
            "BoundingBox3D Orientation Quat Z": 0.955956226084236,
            "ObjectType": "TRAFFIC_SIGN",
            "Occluded": {
                "F_MIDRANGECAM_C": 0.9564387798309326
            },
            "Truncated": 0,
            "ObjectMeta": {
                "SourceID": 618,
                "SubType": "us_white_ground_rectangle_unknown",
                "Text": "",
                "OcrVersion": 10006
            }
        },
        {
            "ActorName": "TRAFFIC_SIGN 619",
            "ObjectId": 619,
            "BoundingBox3D Origin X": 104.053360452368,
            "BoundingBox3D Origin Y": -3.857498448574916,
            "BoundingBox3D Origin Z": 3.152478377334773,
            "BoundingBox3D Extent X": 0.1,
            "BoundingBox3D Extent Y": 0.6539907426792017,
            "BoundingBox3D Extent Z": 1.2534023493860695,
            "BoundingBox3D Orientation Quat W": 0.0670122143248621,
            "BoundingBox3D Orientation Quat X": -0.000991236281457,
            "BoundingBox3D Orientation Quat Y": 0.0121456977016607,
            "BoundingBox3D Orientation Quat Z": 0.9976777348469058,
            "ObjectType": "TRAFFIC_SIGN",
            "Occluded": {
                "F_MIDRANGECAM_C": 0.0010813500266522
            },
            "Truncated": 0,
            "ObjectMeta": {
                "SourceID": 619,
                "SubType": "us_speedlimit_20",
                "Text": "SCHOOL CED UMIT 20",
                "OcrVersion": 10006
            }
        },
        {
            "ActorName": "TRAFFIC_SIGN 620",
            "ObjectId": 620,
            "BoundingBox3D Origin X": 120.51289073562248,
            "BoundingBox3D Origin Y": -7.033764024934499,
            "BoundingBox3D Origin Z": 2.6266092993319035,
            "BoundingBox3D Extent X": 0.0999999999999999,
            "BoundingBox3D Extent Y": 0.4680118431516936,
            "BoundingBox3D Extent Z": 0.6304466963182337,
            "BoundingBox3D Orientation Quat W": 0.3556735064074795,
            "BoundingBox3D Orientation Quat X": -0.0044980460884198,
            "BoundingBox3D Orientation Quat Y": 0.0113267076036152,
            "BoundingBox3D Orientation Quat Z": 0.9345308074729574,
            "ObjectType": "TRAFFIC_SIGN",
            "Occluded": {
                "F_MIDRANGECAM_C": 0.9997851252555848
            },
            "Truncated": 0,
            "ObjectMeta": {
                "SourceID": 620,
                "SubType": "us_white_ground_rectangle_unknown",
                "Text": "",
                "OcrVersion": 10006
            }
        },
        {
            "ActorName": "TRAFFIC_SIGN 621",
            "ObjectId": 621,
            "BoundingBox3D Origin X": 175.6479954347392,
            "BoundingBox3D Origin Y": 12.311934024270158,
            "BoundingBox3D Origin Z": 2.004853058606386,
            "BoundingBox3D Extent X": 0.1,
            "BoundingBox3D Extent Y": 0.7125868482925369,
            "BoundingBox3D Extent Z": 0.551406407640237,
            "BoundingBox3D Orientation Quat W": -0.3484590967368942,
            "BoundingBox3D Orientation Quat X": 0.0040978649958802,
            "BoundingBox3D Orientation Quat Y": 0.0114846990087833,
            "BoundingBox3D Orientation Quat Z": 0.9372446676788622,
            "ObjectType": "TRAFFIC_SIGN",
            "Occluded": {
                "F_MIDRANGECAM_C": 0.9976698756217957
            },
            "Truncated": 0,
            "ObjectMeta": {
                "SourceID": 621,
                "SubType": "unknown",
                "Text": "",
                "OcrVersion": 10006
            }
        },
        {
            "ActorName": "TRAFFIC_SIGN 622",
            "ObjectId": 622,
            "BoundingBox3D Origin X": 175.7569113036775,
            "BoundingBox3D Origin Y": 12.297121317882556,
            "BoundingBox3D Origin Z": 2.7093834849074483,
            "BoundingBox3D Extent X": 0.1,
            "BoundingBox3D Extent Y": 0.7699283456301522,
            "BoundingBox3D Extent Z": 0.7326051227842014,
            "BoundingBox3D Orientation Quat W": -0.4254075639292186,
            "BoundingBox3D Orientation Quat X": 0.0050249620423001,
            "BoundingBox3D Orientation Quat Y": 0.0110971310841534,
            "BoundingBox3D Orientation Quat Z": 0.904919890371508,
            "ObjectType": "TRAFFIC_SIGN",
            "Occluded": {
                "F_MIDRANGECAM_C": 0.9986170530319214
            },
            "Truncated": 0,
            "ObjectMeta": {
                "SourceID": 622,
                "SubType": "us_yellow_ground_diamond_unknown",
                "Text": "",
                "OcrVersion": 10006
            }
        },
        {
            "ActorName": "TRAFFIC_SIGN 623",
            "ObjectId": 623,
            "BoundingBox3D Origin X": 160.6033899021536,
            "BoundingBox3D Origin Y": 16.13669856407796,
            "BoundingBox3D Origin Z": 2.5832474334165454,
            "BoundingBox3D Extent X": 0.0999999999999999,
            "BoundingBox3D Extent Y": 0.517312703930747,
            "BoundingBox3D Extent Z": 0.6851651853833185,
            "BoundingBox3D Orientation Quat W": -0.4164646466937156,
            "BoundingBox3D Orientation Quat X": 0.0049113489224977,
            "BoundingBox3D Orientation Quat Y": 0.0111456865935347,
            "BoundingBox3D Orientation Quat Z": 0.9090703220193688,
            "ObjectType": "TRAFFIC_SIGN",
            "Occluded": {
                "F_MIDRANGECAM_C": 0.99919456243515
            },
            "Truncated": 0,
            "ObjectMeta": {
                "SourceID": 623,
                "SubType": "unknown",
                "Text": "",
                "OcrVersion": 10006
            }
        },
        {
            "ActorName": "TRAFFIC_SIGN 624",
            "ObjectId": 624,
            "BoundingBox3D Origin X": 180.1872640731536,
            "BoundingBox3D Origin Y": -9.062576998985604,
            "BoundingBox3D Origin Z": 2.27443446777761,
            "BoundingBox3D Extent X": 0.1,
            "BoundingBox3D Extent Y": 0.7042827814633992,
            "BoundingBox3D Extent Z": 0.4830502635892186,
            "BoundingBox3D Orientation Quat W": 0.4326923853422193,
            "BoundingBox3D Orientation Quat X": -0.0054254814961093,
            "BoundingBox3D Orientation Quat Y": 0.010911931143023,
            "BoundingBox3D Orientation Quat Z": 0.901459257857018,
            "ObjectType": "TRAFFIC_SIGN",
            "Occluded": {
                "F_MIDRANGECAM_C": 0.999557077884674
            },
            "Truncated": 0,
            "ObjectMeta": {
                "SourceID": 624,
                "SubType": "unknown",
                "Text": "",
                "OcrVersion": 10006
            }
        },
        {
            "ActorName": "TRAFFIC_SIGN 625",
            "ObjectId": 625,
            "BoundingBox3D Origin X": 195.16872520006973,
            "BoundingBox3D Origin Y": -3.28237348338007,
            "BoundingBox3D Origin Z": 2.941409236751497,
            "BoundingBox3D Extent X": 0.1,
            "BoundingBox3D Extent Y": 0.4589120999965893,
            "BoundingBox3D Extent Z": 0.4812655381028048,
            "BoundingBox3D Orientation Quat W": 0.0881992929409221,
            "BoundingBox3D Orientation Quat X": -0.0012400734846119,
            "BoundingBox3D Orientation Quat Y": 0.0121224080463228,
            "BoundingBox3D Orientation Quat Z": 0.9960283099217772,
            "ObjectType": "TRAFFIC_SIGN",
            "Occluded": {
                "F_MIDRANGECAM_C": 0.9962132573127748
            },
            "Truncated": 0,
            "ObjectMeta": {
                "SourceID": 625,
                "SubType": "us_yellow_ground_diamond_unknown",
                "Text": "",
                "OcrVersion": 10006
            }
        }
    ],
    "FrameId": 37005,
    "Timestamp": 0,
    "TimestampMiddle": 0,
    "VERSION": 10006
}