{
    "CapturedObjects": [
        {
            "ActorName": "TRAFFIC_LIGHT 388",
            "ObjectId": 388,
            "BoundingBox3D Origin X": 92.46884926237544,
            "BoundingBox3D Origin Y": 1.081818148260936,
            "BoundingBox3D Origin Z": 6.113401592709124,
            "BoundingBox3D Extent X": 0.6543829509621388,
            "BoundingBox3D Extent Y": 0.6543829509621388,
            "BoundingBox3D Extent Z": 1.3917170339048612,
            "BoundingBox3D Orientation Quat W": 0.001810008982304951,
            "BoundingBox3D Orientation Quat X": -0.005562842043741176,
            "BoundingBox3D Orientation Quat Y": 1.0068966355080865e-05,
            "BoundingBox3D Orientation Quat Z": 0.9999828891308572,
            "ObjectType": "TRAFFIC_LIGHT",
            "Occluded": {
                "F_LONGRANGECAM_C": 2.6403864694657386e-07
            },
            "Truncated": 0,
            "ObjectMeta": {
                "SourceID": 388,
                "SubType": "v-3line",
                "Lights": [
                    {
                        "state": "off",
                        "mask": "full",
                        "color": "unknown"
                    },
                    {
                        "state": "off",
                        "mask": "full",
                        "color": "unknown"
                    },
                    {
                        "state": "on",
                        "mask": "full",
                        "color": "green"
                    }
                ],
                "subject": "vehicles"
            }
        },
        {
            "ActorName": "TRAFFIC_LIGHT 389",
            "ObjectId": 389,
            "BoundingBox3D Origin X": 91.9743579484093,
            "BoundingBox3D Origin Y": -5.017173353757244,
            "BoundingBox3D Origin Z": 3.5258958423510194,
            "BoundingBox3D Extent X": 0.3629398937562062,
            "BoundingBox3D Extent Y": 0.3629398937562062,
            "BoundingBox3D Extent Z": 0.814261300740788,
            "BoundingBox3D Orientation Quat W": 0.001976112683109922,
            "BoundingBox3D Orientation Quat X": -0.002969938172941223,
            "BoundingBox3D Orientation Quat Y": 5.868969834767876e-06,
            "BoundingBox3D Orientation Quat Z": 0.9999936371854912,
            "ObjectType": "TRAFFIC_LIGHT",
            "Occluded": {
                "F_LONGRANGECAM_C": 9.887870874081273e-06
            },
            "Truncated": 0,
            "ObjectMeta": {
                "SourceID": 389,
                "SubType": "v-3line",
                "Lights": [
                    {
                        "state": "off",
                        "mask": "full",
                        "color": "unknown"
                    },
                    {
                        "state": "off",
                        "mask": "full",
                        "color": "unknown"
                    },
                    {
                        "state": "on",
                        "mask": "full",
                        "color": "green"
                    }
                ],
                "subject": "vehicles"
            }
        }
    ],
    "FrameId": 36956,
    "Timestamp": 0,
    "TimestampMiddle": 0,
    "VERSION": 10306
}